{
  "dct_title_s": "Map of Wapello County, Iowa, 1893",
  "dct_description_sm": [
    "1 map on 6 sheets"
  ],
  "dct_language_sm": [
    "eng"
  ],
  "dct_creator_sm": [
    "Allen, C. R."
  ],
  "dct_publisher_sm": [
    "C.R. Allen Engr & Surveyor"
  ],
  "schema_provider_s": "University of Iowa",
  "gbl_resourceClass_sm": [
    "Maps"
  ],
  "dcat_keyword_sm": [
    "County maps"
  ],
  "dct_temporal_sm": [
    "1890-1900"
  ],
  "dct_issued_s": "1893",
  "gbl_indexYear_im": [
    "1890"
  ],
  "gbl_dateRange_drsim": [
    "[1890 TO 1900]"
  ],
  "dct_spatial_sm": [
    "Iowa--Wapello County",
    "Iowa"
  ],
  "locn_geometry": "POLYGON((-92.64036 41.16266, -92.17898 41.16266, -92.17898 40.89887, -92.64036 40.89887, -92.64036 41.16266))",
  "dcat_bbox": "ENVELOPE(-92.64036,-92.17898,41.16266,40.89887)",
  "dcat_centroid": "41.030765,-92.40967",
  "pcdm_memberOf_sm": [
    "64bd8c4c-8e60-4956-b43d-bdc3f93db488"
  ],
  "dct_isPartOf_sm": [
    "03d-01-05",
    "03d-01"
  ],
  "dct_rights_sm": [
    "Material in the public domain. No restrictions on use."
  ],
  "dct_accessRights_s": "Public",
  "dct_format_s": "JPEG",
  "dct_references_s": "{\"http://schema.org/url\":\"https://digital.lib.uiowa.edu/islandora/object/ui%3Asheetmaps_177\"}",
  "id": "ui_sheetmaps_177",
  "dct_identifier_sm": [
    "G4153.W2 1893 .A45",
    "index.cpd",
    "(OCoLC)190892948",
    "31858054661099",
    "4245681",
    "sheetmaps_177"
  ],
  "gbl_mdVersion_s": "Aardvark"
}